deepzoomup/__init__.py
deepzoomup/_nbdev.py
deepzoomup/backblaze.py
deepzoomup/deepzoom.py
deepzoomup/dzi.py
dzi2b2/__init__.py
dzi2b2/_nbdev.py
dzi2b2/backblaze.py
deepzoomup-0.1.2.dist-info/LICENSE
deepzoomup-0.1.2.dist-info/METADATA
deepzoomup-0.1.2.dist-info/WHEEL
deepzoomup-0.1.2.dist-info/entry_points.txt
deepzoomup-0.1.2.dist-info/top_level.txt
deepzoomup-0.1.2.dist-info/RECORD
