Metadata-Version: 2.1
Name: deepzoomup
Version: 0.1.2
Summary: Publish your deep zoom images via Backblaze cloud online
Home-page: https://github.com/fligt/deepzoomup/tree/master/
Author: Frank Ligterink
Author-email: frank.ligterink@gmail.com
License: MIT License
Keywords: deep-zoom backblaze
Platform: UNKNOWN
Classifier: Development Status :: 4 - Beta
Classifier: Intended Audience :: Developers
Classifier: License :: OSI Approved :: MIT License
Classifier: Natural Language :: English
Classifier: Programming Language :: Python :: 3.7
Classifier: Programming Language :: Python :: 3.8
Requires-Python: >=3.7
Requires-Dist: pyvips
Requires-Dist: b2sdk
